lexifuzz_ner/__init__.py
lexifuzz_ner/ner.py
lexifuzz_ner-0.0.8.dist-info/LICENSE
lexifuzz_ner-0.0.8.dist-info/METADATA
lexifuzz_ner-0.0.8.dist-info/WHEEL
lexifuzz_ner-0.0.8.dist-info/RECORD
