Metadata-Version: 2.1
Name: lexifuzz-ner
Version: 0.0.8
Summary: Python package for detecting entities in text based on a dictionary and fuzzy similarity
Home-page: https://github.com/hanifabd/lexifuzz-ner
Keywords: ktp,segmentation,segmentasi,id-card,identity-card
Author: Hanif Yuli Abdillah P
Author-email: hanifabd23@gmail.com
Requires-Python: >=3.7
Classifier: License :: OSI Approved :: MIT License
Classifier: Operating System :: OS Independent
Classifier: Programming Language :: Python :: 3
Classifier: Programming Language :: Python :: 3.7
Classifier: Programming Language :: Python :: 3.8
Classifier: Programming Language :: Python :: 3.9
Classifier: Programming Language :: Python :: 3.10
Classifier: Programming Language :: Python :: 3.11
Classifier: Programming Language :: Python :: 3.12
Requires-Dist: nltk (==3.8.1)
Requires-Dist: thefuzz (==0.20.0)
Project-URL: Repository, https://github.com/hanifabd/lexifuzz-ner
